lenstronomy/__init__.py
lenstronomy/Analysis/__init__.py
lenstronomy/Analysis/lens_analysis.py
lenstronomy/Analysis/lens_properties.py
lenstronomy/Cosmo/__init__.py
lenstronomy/Cosmo/background.py
lenstronomy/Cosmo/lens_cosmo.py
lenstronomy/Data/__init__.py
lenstronomy/Data/coord_transforms.py
lenstronomy/Data/imaging_data.py
lenstronomy/Extensions/__init__.py
lenstronomy/Extensions/CosmoSampling/__init__.py
lenstronomy/Extensions/CosmoSampling/cosmo_chain.py
lenstronomy/Extensions/CosmoSampling/cosmo_properties_pycosmo.py
lenstronomy/Extensions/CosmoSampling/cosmo_solver.py
lenstronomy/Extensions/CosmoSampling/time_delay_sampling.py
lenstronomy/Extensions/Itterative/__init__.py
lenstronomy/Extensions/Itterative/iterative_lens.py
lenstronomy/Extensions/Itterative/iterative_source.py
lenstronomy/Extensions/Plots/__init__.py
lenstronomy/Extensions/Plots/output_plots.py
lenstronomy/Extensions/Scripts/__init__.py
lenstronomy/Extensions/Scripts/compute_map.py
lenstronomy/Extensions/Scripts/mcmc_script.py
lenstronomy/Extensions/Scripts/monch_array_script.py
lenstronomy/Extensions/Scripts/monch_map_script.py
lenstronomy/Extensions/Scripts/run_sequence.py
lenstronomy/Extensions/Scripts/submit_random.py
lenstronomy/Extensions/SimulationAPI/__init__.py
lenstronomy/Extensions/SimulationAPI/multiband.py
lenstronomy/Extensions/SimulationAPI/simulations.py
lenstronomy/Extensions/Substructure/__init__.py
lenstronomy/Extensions/Substructure/clump_detection.py
lenstronomy/Extensions/Substructure/sensitivity.py
lenstronomy/Extensions/Substructure/sensitivity_map.py
lenstronomy/GalKin/LOS_dispersion.py
lenstronomy/GalKin/__init__.py
lenstronomy/GalKin/anisotropy.py
lenstronomy/GalKin/aperture.py
lenstronomy/GalKin/cosmo.py
lenstronomy/GalKin/galkin.py
lenstronomy/GalKin/galkin_old.py
lenstronomy/GalKin/jeans_equation.py
lenstronomy/GalKin/light_profile.py
lenstronomy/GalKin/mass_profile.py
lenstronomy/GalKin/velocity_util.py
lenstronomy-0.0.1.dist-info/.DS_Store
lenstronomy-0.0.1.dist-info/DESCRIPTION.rst
lenstronomy-0.0.1.dist-info/METADATA
lenstronomy-0.0.1.dist-info/RECORD
lenstronomy-0.0.1.dist-info/WHEEL
lenstronomy-0.0.1.dist-info/metadata.json
lenstronomy-0.0.1.dist-info/top_level.txt
