Metadata-Version: 2.0
Name: lenstronomy
Version: 0.0.1
Summary: Strong lens modeling package.
Home-page: https://github.com/sibirrer/lenstronomy
Author: Simon Birrer
Author-email: sibirrer@gmail.com
License: MIT
Download-URL: https://github.com/sibirrer/lenstronomy/archive/0.0.1.tar.gz
Keywords: lenstronomy
Platform: UNKNOWN
Classifier: Development Status :: 2 - Pre-Alpha
Classifier: Intended Audience :: Science/Research
Classifier: Intended Audience :: Developers
Classifier: Natural Language :: English
Classifier: Programming Language :: Python :: 2
Classifier: Programming Language :: Python :: 2.7
Classifier: Programming Language :: Python :: 3
Classifier: Programming Language :: Python :: 3.5
Requires-Dist: configparser
Requires-Dist: numpy (>=1.13)
Requires-Dist: scipy (>=0.14.0)
